{
 "allow_comments": 0,
 "allow_delete": 0,
 "allow_edit": 0,
 "allow_incomplete": 0,
 "allow_multiple": 0,
 "allow_print": 0,
 "anonymous": 0,
 "apply_document_permissions": 0,
 "button_label": "Save",
 "condition_json": "[]",
 "creation": "2025-03-04 13:05:42.532320",
 "doc_type": "Queue Call",
 "docstatus": 0,
 "doctype": "Web Form",
 "hide_footer": 0,
 "hide_navbar": 0,
 "idx": 0,
 "introduction_text": "<div class=\"ql-editor read-mode\"><p><strong style=\"font-size: 96px;\"> &nbsp; List of Queues</strong></p></div>",
 "is_standard": 1,
 "list_columns": [],
 "login_required": 0,
 "max_attachment_size": 0,
 "modified": "2025-03-04 13:05:46.573049",
 "modified_by": "lijsamuael@gmail.com",
 "module": "Queue Management System",
 "name": "queue-list",
 "owner": "lijsamuael@gmail.com",
 "published": 1,
 "route": "queue-list",
 "show_attachments": 0,
 "show_list": 0,
 "show_sidebar": 0,
 "title": "Queue List",
 "web_form_fields": [
  {
   "allow_read_on_all_link_options": 0,
   "fieldname": "ticket_number",
   "fieldtype": "Link",
   "hidden": 0,
   "label": "Ticket Number",
   "max_length": 0,
   "max_value": 0,
   "options": "Queue",
   "precision": "",
   "read_only": 0,
   "reqd": 0,
   "show_in_filter": 0
  },
  {
   "allow_read_on_all_link_options": 0,
   "fieldname": "called_time",
   "fieldtype": "Datetime",
   "hidden": 0,
   "label": "Called Time",
   "max_length": 0,
   "max_value": 0,
   "precision": "",
   "read_only": 0,
   "reqd": 0,
   "show_in_filter": 0
  },
  {
   "allow_read_on_all_link_options": 0,
   "fieldname": "assigned_office",
   "fieldtype": "Link",
   "hidden": 0,
   "label": "Assigned Office",
   "max_length": 0,
   "max_value": 0,
   "options": "Office",
   "precision": "",
   "read_only": 0,
   "reqd": 0,
   "show_in_filter": 0
  }
 ]
}